entrypoint.py
launcher/__init__.py
launcher/launcher_entry.py
launcher/app/__init__.py
launcher/app/app_controller.py
launcher/app/app_model.py
launcher/app/launcher_app.py
launcher/app/web_app.py
launcher/static/favicon.ico
launcher/static/css/layout.css
launcher/static/css/style.css
launcher/static/img/octobot.png
launcher/static/img/svg/arrow_left.svg
launcher/static/img/svg/arrow_right.svg
launcher/static/img/svg/octobot.svg
launcher/static/js/commons.js
launcher/templates/bot_card.html
launcher/templates/footer.html
launcher/templates/index.html
launcher/templates/launcher_card.html
launcher/templates/layout.html
launcher/templates/news_card.html
launcher/tools/__init__.py
launcher/tools/environment.py
launcher/tools/executor.py
launcher/tools/github.py
launcher/tools/octobot_connector.py
launcher/tools/version.py
OctoBot_Launcher-2.0.4.dist-info/LICENSE
OctoBot_Launcher-2.0.4.dist-info/METADATA
OctoBot_Launcher-2.0.4.dist-info/WHEEL
OctoBot_Launcher-2.0.4.dist-info/entry_points.txt
OctoBot_Launcher-2.0.4.dist-info/top_level.txt
OctoBot_Launcher-2.0.4.dist-info/RECORD
