Metadata-Version: 2.1
Name: OctoBot-Launcher
Version: 2.0.4
Summary: OctoBot project launcher
Home-page: https://github.com/Drakkar-Software/OctoBot-Launcher
Author: Drakkar-Software
Author-email: drakkar-software@protonmail.com
License: LGPL-3.0
Platform: UNKNOWN
Classifier: Development Status :: 5 - Production/Stable
Classifier: Operating System :: OS Independent
Classifier: Operating System :: MacOS :: MacOS X
Classifier: Operating System :: Microsoft :: Windows
Classifier: Operating System :: POSIX
Classifier: Programming Language :: Python :: 3.7
Requires-Python: >=3.7.2
Requires-Dist: future
Requires-Dist: requests
Requires-Dist: flask
